stackarator/__init__.py
stackarator/dist_ellipse.py
stackarator/stackarator.py
stackarator-0.0.6.dist-info/LICENSE.md
stackarator-0.0.6.dist-info/METADATA
stackarator-0.0.6.dist-info/WHEEL
stackarator-0.0.6.dist-info/top_level.txt
stackarator-0.0.6.dist-info/zip-safe
stackarator-0.0.6.dist-info/RECORD
