Metadata-Version: 2.1
Name: stackarator
Version: 0.0.6
Summary: A tool for stacking interferometric data of extended sources (such as nearby galaxies) to extract weak emission lines.
Home-page: https://github.com/TimothyADavis/stackarator
Author: Timothy A. Davis
Author-email: DavisT@cardiff.ac.uk
License: MIT
Classifier: Development Status :: 4 - Beta
Classifier: License :: OSI Approved :: MIT License
Classifier: Programming Language :: Python :: 3
Classifier: Operating System :: OS Independent
License-File: LICENSE.md
Requires-Dist: numpy
Requires-Dist: tqdm
Requires-Dist: scipy
Requires-Dist: astropy
Requires-Dist: spectral-cube
